hiss/__init__.py
hiss/cli/__init__.py
hiss/cli/config.py
hiss/cli/magic.py
hiss/cli/virtualenv.py
hiss_repl-4.0.1.dist-info/LICENSE
hiss_repl-4.0.1.dist-info/METADATA
hiss_repl-4.0.1.dist-info/WHEEL
hiss_repl-4.0.1.dist-info/entry_points.txt
hiss_repl-4.0.1.dist-info/top_level.txt
hiss_repl-4.0.1.dist-info/RECORD
